domscribe/__init__.py
domscribe/ast_utils.py
domscribe/converter.py
domscribe/dom_utils.py
domscribe/html_to_markdown_ast.py
domscribe/markdown_ast_to_string.py
domscribe/markdown_types.py
domscribe/url_utils.py
domscribe-0.1.3.dist-info/METADATA
domscribe-0.1.3.dist-info/WHEEL
domscribe-0.1.3.dist-info/top_level.txt
domscribe-0.1.3.dist-info/RECORD
