Metadata-Version: 2.1
Name: domscribe
Version: 0.1.3
Summary: A Python library for converting HTML to semantic Markdown
Author-email: Slava Vishnyakov <bomboze@gmail.com>
Project-URL: Homepage, https://github.com/slava-vishnyakov/domscribe
Project-URL: Bug Tracker, https://github.com/slava-vishnyakov/domscribe/issues
Classifier: Programming Language :: Python :: 3
Classifier: License :: OSI Approved :: MIT License
Classifier: Operating System :: OS Independent
Requires-Python: >=3.7
Requires-Dist: beautifulsoup4
Requires-Dist: requests
